ivy/__init__.py
ivy/__main__.py
ivy/events.py
ivy/extensions.py
ivy/filters.py
ivy/hashes.py
ivy/nodes.py
ivy/renderers.py
ivy/site.py
ivy/templates.py
ivy/utils.py
ivy/bundle/site.py
ivy/bundle/inc/menu.md
ivy/bundle/lib/debug/license.txt
ivy/bundle/lib/debug/readme.md
ivy/bundle/lib/debug/resources/debug.css
ivy/bundle/lib/debug/resources/pygments.css
ivy/bundle/lib/debug/templates/node.ibis
ivy/bundle/lib/graphite/license.txt
ivy/bundle/lib/graphite/readme.md
ivy/bundle/lib/graphite/resources/assets/fonts.css
ivy/bundle/lib/graphite/resources/assets/graphite.css
ivy/bundle/lib/graphite/resources/assets/pygments.css
ivy/bundle/lib/graphite/resources/assets/fonts/CrimsonText-Bold.ttf
ivy/bundle/lib/graphite/resources/assets/fonts/CrimsonText-Bold.woff2
ivy/bundle/lib/graphite/resources/assets/fonts/CrimsonText-BoldItalic.ttf
ivy/bundle/lib/graphite/resources/assets/fonts/CrimsonText-BoldItalic.woff2
ivy/bundle/lib/graphite/resources/assets/fonts/CrimsonText-Italic.ttf
ivy/bundle/lib/graphite/resources/assets/fonts/CrimsonText-Italic.woff2
ivy/bundle/lib/graphite/resources/assets/fonts/CrimsonText-Regular.ttf
ivy/bundle/lib/graphite/resources/assets/fonts/CrimsonText-Regular.woff2
ivy/bundle/lib/graphite/resources/assets/fonts/CrimsonText-SemiBold.ttf
ivy/bundle/lib/graphite/resources/assets/fonts/CrimsonText-SemiBold.woff2
ivy/bundle/lib/graphite/resources/assets/fonts/CrimsonText-SemiBoldItalic.ttf
ivy/bundle/lib/graphite/resources/assets/fonts/CrimsonText-SemiBoldItalic.woff2
ivy/bundle/lib/graphite/resources/assets/fonts/OFL.txt
ivy/bundle/lib/graphite/templates/node.ibis
ivy/bundle/src/about.md
ivy/bundle/src/index.stx
ivy/bundle/src/parent.md
ivy/bundle/src/parent/child-one.md
ivy/bundle/src/parent/child-two.md
ivy/cli/__init__.py
ivy/cli/add.py
ivy/cli/build.py
ivy/cli/clear.py
ivy/cli/deploy.py
ivy/cli/init.py
ivy/cli/open.py
ivy/cli/serve.py
ivy/cli/tree.py
ivy/cli/watch.py
ivy/extensions/ivy_automenu.py
ivy/extensions/ivy_ibis.py
ivy-6.4.1.dist-info/METADATA
ivy-6.4.1.dist-info/WHEEL
ivy-6.4.1.dist-info/entry_points.txt
ivy-6.4.1.dist-info/top_level.txt
ivy-6.4.1.dist-info/RECORD
